{
    "articles": [
        {
            "id": "31741981-ae15-4ba0-9d43-d2bca1a4142e",
            "title": "投资界的哥德巴赫猜想：如何最公平的估值贵州茅台与招商银行？（市赚率实战第2篇）",
            "author": "ericwarn丁宁",
            "content": "来源：雪球App，作者：ericwarn丁宁，（https://xueqiu.com/9363345092/311274853）\n\n#### 有幸获得雪球十大影响力提名，烦请各位每天投我一票，感恩感谢。\n\n#### 投票地址：网页链接\n\n#### 为了拉票，继续发一个市赚率实战系列文章，纯纯干货，不掺水。\n\n********** 正文分割线 **********\n\n为了学习巴菲特，我发明了一个叫作“市赚率”的估值参数。其公式为：市赚率=市盈率/净资产收益率（PR=PE/ROE）。考虑到ROE是个百分数，所以市赚率的真实公式其实是：PR=PE/ROE/100。当市赚率等于1PR为合理估值，大于1PR和小于1PR则为高估和低估。上世纪80年代，巴菲特两次建仓可口可乐。1988年的市赚率估值是0.474PR，1989年的市赚率估值是0.326PR。两年平均下来，刚好就是0.4PR。比较巧合的是，从那时起，用“40美分买入1美元”就成了巴菲特的口头禅。再加上巴菲特90%的投资案例均符合市赚率低估买入标准，所以市赚率很可能就是巴菲特的投资秘密。巴菲特4折5折6折买股，我也照猫画虎4折5折6折买股。\n\n![Image](https://xqimg.imedao.com/192fc64b402815bb3fe24d0c.png!800.jpg)\n\n发明市赚率之后，我发现：如果用在国内价投标杆贵州茅台身上，几乎可以用神奇来形容。用后视镜来看，2016、2018、2024这三年的熊市底部，几乎都跌到了4折5折6折的买入区间。反观2018和2019这两年的牛市顶部，则都涨到了1.0PR以上。2021年的牛市顶部，则更是涨到了2.0PR。如此一来，杀跌到6折附近就开始越跌越买，上涨到正价之后就开始越涨越卖，几乎成了致胜法宝。我甚至曾经狂妄的误以为：股市就是我的提款机。\n\n![Image](https://xqimg.imedao.com/192fc64b9c768aaf3fbf60dc.png!800.jpg)\n\n然而令人意外意外的是，如果再把目光转移到其他股票身上，则会出现啪啪打脸的情况。以美的集团为例，即便是牛市，市赚率估值也只能涨到0.8PR多点，根本涨不到1.0PR。同一时期的招行银行则更是如此，最高的市赚率只能上涨到0.6PR多点，距离1.0PR的合理估值则更是遥不可及。\n\n为什么呢？因为招商银行被市场先生称之为“赚假钱”的公司，多年平均股利支付率只有30%。反观美的集团，则是“半真半假”的公司，多年平均股利支付率只有40%。只有贵州茅台才是“赚真钱”的公司，多年平均股利支付率高达50%。\n\n有鉴于此，我又以多年平均股利支付率高达50%的贵州茅台为标杆，加入了N这个修正系数（PR=N*PE/ROE）。股利支付率≥50%的企业，修正系数为1.0（50%除50%）；股利支付率≤25%的企业，修正系数为2.0（50%除以25%）；50%＞股利支付率＞25%的企业，例如33%的企业，修正系数为1.5（50%除以33%）。修正市赚率最大的目的，就是解决贵州茅台与招商银行的估值差问题，既然目的达到了，也就不再苛求。所以修正系数的最大值和最小值，也仅仅相差一倍而已。修正市赚率仅适用于ROE稳定的价值股，周期股别用（因为景气年份才会加大分红）、科技股别用（因为经常用回购代替分红）、成长股别用（因为需要留存利润用于成长）。\n\n贵州茅台的多年平均ROE是30%，多年平均股利支付率是50%。修正系数就是1.0，合理估值就是30PE左右。前几年漂亮50受宠，30PE以上也时常见到。\n\n招商银行的多年平均ROE是15%，多年平均股利支付率是33%。修正系数就是1.5（50%除以33%），合理估值就是10PE左右（15除以1.5）。最近几年银行股失宠，所以10PE就算是封顶了。\n\n接下来，见证奇迹的时刻到了。2018年底至2019年初的熊市里，很多价值股都出现了大幅下跌。以熊市最低价为例，只看市盈率，肯定买入中国建筑；只看市赚率，肯定买美的集团、中国平安、招商银行、中国建筑，却可能无视贵州茅台。只看修正市赚率，中国建筑就会被淘汰，贵州茅台反倒会被入选。至于后期走势也是如此，一年之后的2019年底，贵州茅台、美的集团、中国平安、招商银行都出现了至少50%的上涨，只有中国建筑趴在了原地不动！\n\n![Image](https://xqimg.imedao.com/192fc64b608815bc3fece199.png!800.jpg)\n\n最后要说的是，市赚率属于科学公式，因为可以用DCF或PEG进行解析（后期文章会有详解）。反观修正市赚率，则是经验公式，没什么道理可讲，并且只在最近几年才有效。在国内股市逐步加大回馈股东的大背景下，未来的某一天，修正市赚率将会彻底失效。\n\n最最后要说的是，周期股在进入到景气周期多年之后，如果仍然抠抠搜搜的不肯多分红，就需要修正市赚率进行估值了。尤其是在与同行业股票进行对比时，则更是如此。曾经困扰我很长时间的中煤能源H股和中国神华H股的市赚率估值差，也仅需修正市赚率即可解决！\n\n@今日话题@闭嘴吧超超@博士王神经@曹国公李景隆@直言不讳的勇敢@平和宁境\n\n$贵州茅台(SH600519)$$招商银行(SH600036)$$中国建筑(SH601668)$\n\n扩展阅读：市赚率如何估值周期股：网页链接\n\n扩展阅读：市赚率如何估值银行股：网页链接\n\n扩展阅读：市赚率的四大隐形参数：网页链接\n",
            "tags": [],
            "created_at": 1769571830
        },
        {
            "id": "b82c6fd0-7a5e-4802-bdde-eb5f0afacaf9",
            "title": "巴菲特投资谷歌告诉我们：任何学习市赚率的普通人，都有可能预测巴菲特的买入目标！",
            "author": "ericwarn丁宁",
            "content": "来源：雪球App，作者：ericwarn丁宁，（https://xueqiu.com/9363345092/361939390）\n\n引言：为了学习巴菲特，我发明了市赚率。其公式为：市赚率=市盈率/净资产收益率（PR=PE/ROE/100）。上世纪80年代，巴菲特两次建仓可口可乐。两年平均下来，市赚率刚好就是0.4PR。从那时起，用“40美分买入1美元”就成了股神的口头禅。巴菲特4折5折6折买股，我也4折5折6折买股。并且毫不夸张地说，任何学习市赚率的普通人，都有可能预测巴菲特的买入目标！比如说，最近巴菲特买入谷歌！\n\n![Image](/static/article_images/53b31909-5d2b-4afb-b951-e90a1f316edb.png)\n\n#### 接下来开始事件回溯：\n\n2025年5月8日，第一位球友@高情的盈利小美术馆提醒我谷歌已经到了5折机会了。我的回复是：谷歌确实低估了，要是ROE能稳住，大概率低估，可惜我没有美股账户。\n\n![Image](/static/article_images/3f8b17b5-ecb6-4851-a331-2be4fd6ed8ee.png)\n\n2025年5月8日当天，第二位球友@叁佰1号位看到了这个评论，在雪球建立了一个投资组合，目前收益80%，他觉得太夸张了。（言外之意就是市赚率很神奇）\n\n![Image](/static/article_images/7945a902-658d-4cfa-9983-d9f2fc762bdb.png)\n\n2025年6月21日，第三位球友@LQ的观众提醒我看一下美股，说不定有金矿，比如先前讨论的谷歌。我的回复是：美股开户真的需要提上日程了。\n\n![Image](/static/article_images/0e4ac821-638e-471a-b58d-01c389b94d2f.png)\n\n2025年11月15日，伯克希尔发布三季报，巴菲特将谷歌买成了第十重仓股。在大家的帮助下，我找到了上述三位球友历史留言。这就意味着，只要市值足够大，ROE或ROA足够稳定，管理层足够诚信，市赚率跌至5折左右。任何学习市赚率的普通人，都有可能预测巴菲特的买入目标。比如这次先于巴菲特发掘出谷歌这个投资机会，就并非出自我自己的研究，而是另外三位学习市赚率的球友。更为值得一提的是，巴菲特的持仓成本或许只是低至6折。而5月8日建立投资组合的球友，持仓成本则可低至5折。\n\n#### 接下来，继续引述新闻发布后，各位球友的观点：\n\n第四位球友@红利人生的观点：应该不是巴菲特买的，2022年股东会的时候，巴菲特就说，他的决策不超过25%。考虑到他今年就退休了，很可能是格雷格买的。不过格雷格肯定也是按照巴菲特的投资原则买的。（巴菲特即将退休，大概率会将投资公式传授给旗下投资经理）\n\n![Image](/static/article_images/b9722c51-612c-4a44-b6f1-757911cd19f8.png)\n\n第五位球友@梅本万利读书社的观点：从这里也可以发现机会，后巴菲特时代，只要严格按照巴菲特的投资思路，那么伯克希尔出现5折的投资机会，就是很好的建仓机会。（其他护城河优秀的企业出现5折机会，比如本文的主角谷歌，也同样值得考虑）\n\n![Image](/static/article_images/60caa231-2b40-400c-b4c1-5362f7fc5298.png)\n\n第六位球友@阿星阿接力接力的观点：聪明人早都知道你是对的了，后面一次次的被验证，只有一堆不知变通的人在那纠结，PE除以ROE的意义，他们不信也是好事，当一个指标人尽皆知人人都用，就是失效的时候了。（其实市赚率与巴菲特一直念叨的DCF原理相通）\n\n![Image](/static/article_images/cc4fec79-a7b1-44a3-9d79-d39e6a44583c.png)\n\n综上所述，市赚率很可能就是巴菲特的投资秘密。至于如何用好市赚率，欢迎广大读者持续关注与沟通。\n\n$谷歌A(GOOGL)$$谷歌C(GOOG)$\n\n市赚率估值银行股：网页链接\n\n市赚率估值周期股：网页链接\n\n市赚率估值困境反转股：网页链接\n\n市赚率应对ROE虚高失真：网页链接\n\n市赚率的5大隐形参数：网页链接\n\n风险提示：本文所提到的观点仅代表个人的意见，所涉及标的不作推荐，据此买卖，风险自负。\n",
            "tags": [],
            "created_at": 1769572381,
            "updated_at": 1769572442
        },
        {
            "id": "257df2bd-9bca-4eb0-a0a6-9c2a9012ffab",
            "title": "巴菲特唯一给出准确估值的中国石油，竟然泄露了股神的投资秘密（市赚率实战第3篇）",
            "author": "ericwarn丁宁",
            "content": "来源：雪球App，作者：ericwarn丁宁，（https://xueqiu.com/9363345092/311470518）\n\n#### 有幸获得雪球十大影响力提名，烦请各位每天投我一票，感恩感谢。\n\n#### 投票地址：网页链接\n\n#### 为了拉票，继续发一个市赚率实战系列文章，纯纯干货，不掺水。\n\n********** 正文分割线 **********\n\n为了学习巴菲特，我发明了一个叫作“市赚率”的估值参数。其公式为：市赚率=市盈率/净资产收益率（PR=PE/ROE）。考虑到ROE是个百分数，所以市赚率的真实公式其实是：PR=PE/ROE/100。当市赚率等于1PR为合理估值，大于1PR和小于1PR则为高估和低估。上世纪80年代，巴菲特两次建仓可口可乐。1988年的市赚率估值为0.474PR，1989年的市赚率估值为0.326PR。两年平均下来，刚好就是0.4PR。非常巧合的是，从那时起，用“40美分买入1美元”就成了巴菲特的口头禅，所以市赚率很可能就是巴菲特的投资秘密。巴菲特4折5折6折买股，我也照猫画虎4折5折6折买股。\n\n![Image](/static/article_images/d296718f-1beb-435f-9bfd-ea9f59025689.png)\n\n考虑到PE=PB/ROE，所以市赚率还可推导出第二公式：PR=PB/ROE/ROE/100。在投资周期股时，可以把现值PB和多年ROE平均值代入第二公式，从而计算出周期股的市赚率。\n\n巴菲特唯一给出准确估值的只有中国石油\n\n接下来，书归正传。回顾巴菲特的历年股东信，仅对两家公司公开分析过内在价值，分别是华盛顿邮报和中国石油。前者年代久远，且语焉不详。后者年代更近，且数据详尽。在2007年的股东信里，巴菲特表示，他在2002年和2003年买入的中国石油H股，当时的总市值仅为370亿美元。“查理和我当时都觉得，该公司的内在价值约为1000亿美元。”\n\n![Image](/static/article_images/a5caa7ad-433c-4039-91d5-4fe66318c1be.png)\n\n据了解，中国石油H股是于2000年上市的，所以公开财报只能查到1999年。至于巴菲特的买入时间，则是2002年开始的，并于2003年买定离手。考虑到2003年的年报是在2004年初发布的。所以说，巴菲特在买入中国石油H股时，仅能获得1999～2002年期间的财报数据。在这四年间，中国石油的ROE分别为12.83%、20.23%、15.65%、14.81%，多年平均值则为15.88%。至于2002年的每股净资产，则已达到了1.8元人民币。\n\n![Image](/static/article_images/9577f144-cb43-4d66-905c-d35a74b399c2.png)\n\n另据伯克希尔2003年财报来看，巴菲特共花费4.88亿美元，买入了2338961000股中国石油H股，每股均价0.209美元。当时的美元人民币汇率则为8.277:1，所以每股持仓成本就是1.73元人民币。巴菲特买入时的市净率估值为1.73/1.8=0.96PB。\n\n![Image](/static/article_images/b649843d-e68c-49e1-9e19-0a57962a2272.png)\n\n接下来，见证奇迹的时刻到了。巴菲特买入时的现值市净率约为0.96PB，多年ROE平均值则为15.88%。运用市赚率第二公式（PR=PB/ROE/ROE/100），市赚率=0.96/15.88%/15.88%/100=0.38PR。\n\n前文已经说过，巴菲特投资中国石油H股时，总市值仅为370亿美元，至于1PR市赚率所对应的企业内在价值则可设定为未知数X。顺此脉络，列出一个方程式：0.38/1=370亿/X。经过简单计算，X等于974亿美元。四舍五入之后（英文单词about），刚好就是巴菲特在股东的信当中所宣称的1000亿美元内在价值。\n\n到了2007年，巴菲特陆续卖出中国石油H股。清仓价大约是在0.8PR～1.0PR之间，并实现了四年八倍的投资收益。值得注意的是，当时的中国石油A股尚未上市。假设中国石油的A股当时已经上市了，其实也无需过多考虑A股的估值。跟随巴菲特，以H股为标杆。H股高估之后，一并卖出中国石油A股即可。\n\n周期股都可以用市赚率估值吗？\n\n以中国神华H股和中国海油H股为例，现值PB就摆在那里，所以ROE的取值更为关键！\n\n方案1：取值一个比较完整的萧条+景气周期，也就是2020～2023年，中国神华的4年ROE平均值约为14.40%，中国海油的4年ROE平均值约为16.64%。\n\n方案2：取值一个完整周期，但要去掉一个最高值（2022年），也要去掉一个最低值（2020年），中国神华的剩下两年的ROE平均值则为14.26%，中国海油剩下两年的ROE平均值则为17.46%。\n\n方案3：取值景气周期里的ROE最低值，也就是2021年。中国神华的ROE是13.64%，中国海油那一年的ROE是15.36%。\n\n方案4：最近四个季度ROE之和，也就是TTM ROE。今年一季报过后，中国神华和中国海油先后创出了历史新高。所以当时的TTM ROE就等于2024年第一季度的ROE再加上2023年后三季度的ROE。中国神华的TTM ROE是14.08%，中国海油的TTM ROE是20.09%。\n\n接下来，仍以今年历史新高的股价为例，中国神华H股的市净率大约涨到了1.73PB，中国海油H股的市净率大约涨到了1.47PB。\n\n中国神华H股的4种方案估值：市赚率估值分别是0.83PR、0.85PR、0.93PR、0.87PR。无论是乐观方案还是悲观方案，均出现了0.8PR～1.0PR之间的卖出信号。\n\n中国海油H股的4种方案估值：市赚率估值分别是0.53PR、0.48PR、0.62PR、0.35PR。无论是乐观方案还是悲观方案，均未出现0.8PR～1.0PR之间的卖出信号。\n\n![Image](/static/article_images/6420a111-3888-40fe-8daa-1e5e88dad272.png)\n\n接下来再说说热门股中远海控H股，今日的收盘价大约是0.79PB。景气周期里的ROE最低值则为11.80%（2023年），市赚率=0.79/11.80%/11.80%/100=0.57PR，即便是最保守的估值方案，也仍然显示低估。\n\n运用市赚率投资周期股好用吗？\n\n巴菲特投资中国石油H股：好用（2002～2007年），出现了0.8PR～1.0PR的卖出信号。\n\n上一轮景气周期里，投资中国神华H股和中国海油H股：好用（2016～2018年），出现了0.8PR～1.0PR的卖出信号。\n\n本轮景气周期里，投资中国神华H股：好用（2020～2024年），出现了0.8PR～1.0PR的卖出信号。\n\n本轮景气周期里，投资中国海油H股：未知（2020～2024年），尚未出现0.8PR～1.0PR的卖出信号。\n\n综上所述，目前的好用概率大约是80%，属于大概率事件，但并未达到100%。\n\n最后要说的是，除非是全面牛市，否则一个行业里的股票不可能全面涨到高估，所以还需找一个行业龙头标杆。龙头标杆高估之后，一并卖出所有同行业股票。煤炭行业我选中国神华H股，石油行业我选中国海油H股。前不久，中国神华H股高估了，这也是我今年清仓所有煤炭股的重要原因。\n\n最最后要说的是，每个周期股的背后都有一个直接影响其业绩表现的商品价格。投资煤炭股，需要关注煤价。投资石油股，需要关注油价。虽然很累很累，但却经常可以收获底部N倍的暴利。而在持股过程中，一旦遇到了商品价格崩盘，就需要冷静分析。如果分析结果是景气周期已经结束，就需要及时调整投资策略才行！\n\n@今日话题@闭嘴吧超超@博士王神经@曹国公李景隆@直言不讳的勇敢@平和宁境\n\n$中国神华(01088)$$中国海洋石油(00883)$$中远海控(01919)$\n",
            "tags": [],
            "created_at": 1769572472
        },
        {
            "id": "20e41272-3965-4259-bfa6-4cdf0c2bab4b",
            "title": "投资界的哥德巴赫猜想：如何最公平的估值茅台与银行？巴菲特投资秘密的国内应用（市赚率系列文章第4篇）",
            "author": "ericwarn丁宁",
            "content": "来源：雪球App，作者：ericwarn丁宁，（https://xueqiu.com/9363345092/266453694）\n\n最近在谈公费出书《巴菲特的投资秘密》，刚好又获得了雪球网的“十大新锐用户”提名。为了感谢各位投票的球友，决定“挤出”干货写个系列文章。如果觉得市赚率有用的话，请给我投票，万分感谢。11月7日～11月16日，每天可投一票，相关链接：网页链接\n\n******** 正 文 分 割 线 ********\n\n书归正传，为了学习巴菲特，笔者发明了一个叫作“市赚率”的估值参数。其公式为：市赚率=市盈率/净资产收益率（PR=PE/ROE）。当市赚率等于1PR为合理估值，大于1PR和小于1PR则为高估和低估。上世纪80年代，巴菲特连续两年买入可口可乐，市赚率估值分别为0.474PR和0.326PR，平均值刚好就是0.4PR。从此以后，“40美分买入1美元”就成了巴菲特的口头禅！因此，市赚率很可能就是巴菲特的投资秘密！\n\n![Image](/static/article_images/7b7a7096-a9b9-4ce8-875f-d3a54f53cb59.png)\n\n接下来，问题来了。即便有了市赚率公式，仍然无法最公平的估值茅台与银行。考虑到国企央企无法收购，只能通过股价上涨和股利支付来实现价值回归。所以笔者又以贵州茅台为标杆，加入了N这个修正系数（PR=N*PE/ROE）\n\n●股利支付率≥50%的企业，修正系数为1.0（50%除50%）；●股利支付率≤25%的企业，修正系数为2.0（50%除以25%）；●50%＞股利支付率＞25%的企业，例如40%的企业，修正系数为1.25（50%除以40%）。\n\n接下来，见证奇迹的时刻到了（如下表）。2018年熊市里，很多蓝筹股都出现了大幅下跌。以2018年最低价为例，只看市盈率，肯定买入中国建筑；只看市赚率，肯定买美的、招行、中建，却可能无视茅台和五粮液。只看修正市赚率，中国建筑就会被淘汰，茅台和五粮液反倒会被入选。至于后期走势也是如此，茅台、五粮液、美的、招行都至少翻倍了，只有中建趴在了原地不动！\n\n![Image](/static/article_images/24778c4b-a5c1-4480-9229-dae51dcd331c.png)\n\n不得不说的是，市赚率属于科学公式，因为可以用DCF或PEG进行解析。反观修正市赚率，则是经验公式，没什么道理可讲，并且只在最近几年才有效。在国企央企逐步加大回馈股东的大背景下，未来的某一天，修正市赚率将会彻底失效。\n\n需要注意的是，修正市赚率仅适用于分红稳定的蓝筹股。周期股别用（景气年份就会大比例分红了）、科技股别用（经常用回购代替分红）、成长股别用（资金需要用于成长）。\n\n最后要说的是，考虑到PE=PB/ROE，所以市赚率还可推导出第二公式：PR=PB/ROE/ROE。在估值周期股时，可以把MRQ PB和景气周期里ROE最低的一年代入到第二公式，从而计算出周期股相对保守的市赚率估值。如果周期股在景气年份里并未大比例分红，则需要用第二公式的修正市赚率进行估值（PR=N*PB/ROE/ROE）。以中国神华H和中煤能源H为例，只对比市赚率，中煤H只有神华H的“一半”多点。如果对比修正市赚率，两者就相差不多了。\n\n![Image](/static/article_images/5880889a-cdf4-4716-ae9d-50c19ab9bb5d.png)\n\n市赚率系列文章第1篇：巴菲特的投资秘密：网页链接\n\n市赚率系列文章第2篇：周期股的估值方法：网页链接\n\n市赚率系列文章第3篇：市赚率与DCF折现：网页链接\n\n$贵州茅台(SH600519)$$招商银行(SH600036)$$中国神华(01088)$\n\n@今日话题@勤劳的超超啊@周期及其趋势@陆冲河@博士王神经@曹国公李景隆\n\n![Image](/static/article_images/376428d6-b6bf-451b-a0bd-e5f1649adb42.png)\n",
            "tags": [],
            "created_at": 1769572500
        },
        {
            "id": "454baaa6-a8aa-4335-88b2-5a7d3762cbac",
            "title": "当ROE严重失真时，巴菲特会怎样应对？其实苹果就是答案！（市赚率实战第5篇）",
            "author": "ericwarn丁宁",
            "content": "来源：雪球App，作者：ericwarn丁宁，（https://xueqiu.com/9363345092/311973567）\n\n#### 有幸获得雪球十大影响力提名，烦请各位每天投我一票，感恩感谢。\n\n#### 投票地址：网页链接\n\n#### 为了拉票，继续发一个市赚率实战系列文章，纯纯干货，不掺水。\n\n#### ********** 正文分割线 **********\n\n为了学习巴菲特，我发明了一个叫作“市赚率”的估值参数。其公式为：市赚率=市盈率/净资产收益率（PR=PE/ROE）。考虑到ROE是个百分数，所以市赚率的真实公式其实是：PR=PE/ROE/100。当市赚率等于1PR为合理估值，大于1PR和小于1PR则为高估和低估。上世纪80年代，巴菲特两次建仓可口可乐。1988年的市赚率估值为0.474PR，1989年的市赚率估值为0.326PR。两年平均下来，刚好就是0.4PR。非常巧合的是，从那时起，用“40美分买入1美元”就成了巴菲特的口头禅，所以市赚率很可能就是巴菲特的投资秘密。巴菲特4折5折6折买股，我也照猫画虎4折5折6折买股。\n\n![Image](/static/article_images/31aaed6f-0b6c-4b44-8a3d-5be808b354b1.png)\n\n需要注意的是，当ROE在10%～50%区间时，市赚率才会有效。当ROE虚高失真时，市赚率则需要借助ROA才能进行估值。以苹果为例，2008年至今，最保守的经营策略也是2012年的轻微负债，至于当年的ROE则刚好是ROA的1.5倍。如此一来，借鉴苹果公司就会出现了一个衍生市赚率，其公式为：衍生市赚率=PE/1.5ROA。\n\n![Image](/static/article_images/cffd77f5-9a95-4fdf-9f97-3d32c54466bb.jpg)\n\n2020年，巴菲特在40PE减仓了苹果，那是因为1.54PR的衍生市赚率已经明显高估了。2022年，巴菲特又在20PE回补了苹果，那是因为衍生市赚率已经跌到不到“半价”了。\n\n时间推进到2024年，巴菲特开始大幅减持苹果。考虑到苹果股价已经在35PE附近横盘许久，所以减持价格大概也是35PE，至于2024年财报的ROA则为26.13%。衍生市赚率=PE/1.5ROA=35/(1.5*26.13)=0.89PR。\n\n![Image](/static/article_images/13d9ba2c-bc6d-4aef-9f92-9b9fa1644681.png)\n\n这个时候，有个问题摆在我们面前。2020年的减持价高达1.54PR，2024年的减持价却只有0.89PR，为啥？\n\n因为在低利率环境下，市赚率的合理估值会上移至1.1～1.4PR（DCF测算可得）。2020年巴菲特在1.54PR减持苹果时，正值疫情最严重时期，利率接近为零。芒格当时表示：利率这么低，我宁愿持有（略微高估）的股票！\n\n反观高利率环境下，市赚率的合理估值则会下移至0.7～0.9PR（DCF测算可得）。虽然目前的美元已经降息，但却仍然处于多年高位。上世纪80年代，巴菲特曾在股东信里分析过两个案例，合理估值均为0.8PR左右，也刚好符合当时的高利率环境。\n\n![Image](/static/article_images/3e527fc7-9a93-45fd-886e-26eaa9224bc7.png)\n\n另外要说的是，定量分析只是卖出的原因之一，还需配合定性分析。进入到2024年之后，苹果造车退出、AI落后、竞争对手崛起，股价却不跌反涨，这或许也是巴菲特将其大幅减仓的重要原因之一。\n\n反观国内股市当中，考虑到负债“分红+回购”的案例很少很少，所以ROE虚高失真的现象并不普遍。读者经常提问的重庆啤酒，算是一个典型案例。\n\n前期底部，重庆啤酒50.85元，当时三季报还未发，TTM市盈率为17.92，TTM ROA为22.21%，衍生市赚率=PE/1.5ROA=17.92/(1.5*22.21)=0.54PR。\n\n本周收盘，重庆啤酒65.25元，目前三季报已发，TTM市盈率为23.84，TTM ROA为22.26%，衍生市赚率=PE/1.5ROA=23.84/(1.5*22.26)=0.71PR。\n\n最后要说的是，我个人认为，啤酒的护城河略逊于白酒，所以前期底部的重庆啤酒，我只买了一点观察仓，主要目的还是为了验证衍生市赚率是否可行。此外，衍生市赚率属于经验公式，目前还算有效，但没准哪一天就会失效。\n\n@今日话题@闭嘴吧超超@博士王神经@曹国公李景隆@直言不讳的勇敢@陆冲河\n\n$苹果(AAPL)$$重庆啤酒(SH600132)$\n",
            "tags": [],
            "created_at": 1769572528
        },
        {
            "id": "78faeb30-ce82-45e2-8c0f-f6bb2be1c81d",
            "title": "市赚率绝非万能，还需五大隐形参数来辅助（市赚率实战第6篇）",
            "author": "ericwarn丁宁",
            "content": "来源：雪球App，作者：ericwarn丁宁，（https://xueqiu.com/9363345092/312215356）\n\n#### 有幸获得雪球十大影响力提名，烦请各位每天投我一票，感恩感谢。\n\n#### 投票地址：网页链接\n\n#### 为了拉票，继续发一个市赚率实战系列文章，纯纯干货，不掺水。\n\n#### ********** 正文分割线 **********\n\n为了学习巴菲特，我发明了一个叫作“市赚率”的估值参数。其公式为：市赚率=市盈率/净资产收益率（PR=PE/ROE）。考虑到ROE是个百分数，所以市赚率的真实公式其实是：PR=PE/ROE/100。巴菲特4折5折6折买股，我也照猫画虎4折5折6折买股。\n\n![Image](/static/article_images/b57dce94-e497-416e-b6dc-423dde3a949b.png)\n\n巴菲特唯二给出过内在价值的股票只有华盛顿邮报和中国石油，目前有且仅有市赚率能够完美解析。不过即便如此，市赚率也绝非万能，还需五大隐形参数来辅助！\n\n隐形参数1：增长率\n\n假设有A、B、C三家公司，恒定ROE均为30%，投资者所要做的就是10年前按照1PR市赚率将其从市场先生那里买来，10年后再按照1PR市赚率将其卖回给市场先生。在这10年间，如果A、B、C三家公司的股利支付率分别是100%、50%、0%，并且不收红利税，同时每年分红仍以1PR进行买入。那么，A、B、C三家公司在10年后的投资复利分别为3.33%、16.67%、30%。\n\n![Image](/static/article_images/394880b1-ae7d-4419-97c4-29b6cb4fa62f.png)\n\nA公司的投资复利最低，只有3.33%。它的投资复利与ROE完全无关，只与股息率有关。B公司的投资复利中等，“投资复利=ROE×（1-股利支付率）+股息率=16.67%”。B公司50%的股利支付率，也最为贴近现实生活，前几年的贵州茅台与其很像。C公司的投资复利最高，高达30%。这也符合芒格所说的：“时间拉长，ROE≈投资复利”。但在现实生活中，这样的公司几乎没有。\n\n综上所述，在ROE相对稳定的前提下，增长率越高，投资复利就会越接近ROE；增长率越低，投资复利就会越接近股息率。考虑到案例当中的B公司最为接近现实生活，所以笔者经常会以B公司作为标杆。也就是说，市赚率对于净利润增长率的要求，至少也要达到ROE的一半。举个例子，30%的ROE，多年平均净利润增长率至少也要15%。\n\n![Image](/static/article_images/ef31c587-c324-4a02-a3bc-4595884caa47.png)\n\n看到这里，有些读者会问：为何不将如此重要的增长率作为显形参数？以贵州茅台为例，最近几年的ROE十分稳定，普遍都在30%左右。反观增长率，则在12%～30%之间，极其不稳定。如果把增长率作为显形参数，就会大幅影响估值结果。\n\n![Image](/static/article_images/9b4dd797-8929-43d1-8122-3e5b420166ee.png)\n\n除此之外，如果把安全边际大幅提高，10年前以0.5PR买入，10年后以1PR卖出。如果想要实现20%以上的投资复利，就会发现市赚率对增长率的要求大幅降低。30%的ROE，仅需实现ROE数值1/4的增长率（7.5%）；20%的ROE，仅需实现ROE数值1/3的增长率（6.67%）；15%的ROE，仅需实现ROE数值1/2的增长率（7.5%）。上述3种情况如果模糊正确一下，5折买股时市赚率对增长率的要求就会降低至7%左右。非常巧合的是，巴菲特在2016年投资苹果公司之前，为旗下投资经理托德提出了三个问题。其中一个问题就是：哪些公司未来可以获得7%的复合增长率？这就意味着，如果投资者总能以5折市赚率买股，那么市赚率对增长率的要求便可降低至7%左右！\n\n![Image](/static/article_images/cc10d568-eec0-419b-9492-3c1f5b325d01.png)\n\n隐形参数2：负债率\n\n巴菲特口头上十分厌恶“高负债”，但却买了一堆的保险和银行。不要看他说什么，还要看他做什么。所以跨行业对比负债率，并没有实际意义。有鉴于此，负债率最好不要超过行业平均值，最近几年暴雷的地产股皆是如此，比如恒大。考虑到巴菲特投资富国银行的成功案例，拨备覆盖率低于300%的银行股基本不用考虑。目前来看，六大行里只有农业银行和邮储银行。股份行里则有很多高拨备，比如招商银行。\n\n隐形参数3：利率\n\n巴菲特经常念叨喜欢把长期国债利率作为折现率估值股票。简单来说，就是低利率环境可以提升股票市场对高估值的容忍度，反之亦然。根据DCF计算器的数据测算，低利率环境下，市赚率的合理估值会上移至1.1PR～1.4PR之间。2021年疫情最严重时，美元利率接近为零，美股暴涨。芒格当时表示：利率这么低，我宁愿持有（略微高估的）股票！\n\n反观高利率环境下，市赚率的合理估值则会下移至0.7PR～0.9PR之间。上世纪80年代，巴菲特曾在股东信里分析过两个案例，合理估值均为0.8PR左右，也刚好符合当时的高利率环境。\n\n![Image](/static/article_images/cc3089de-9dea-408a-aeee-593f09e525bf.png)\n\n隐形参数4：股息率\n\n前两年，港币定存利率高达5%，当时再去买股息率低于5%的H股就显得不太明智了。在高利率环境下，投资标的的股息率最好超过利率。这样一来，最起码也能享受到超越银行的“利率”，同时还能享受到企业内在价值的增长，甚至还可能享受到低估股票的估值修复，可谓是一举三得。\n\n不得不说的是，除了ROE，巴菲特在股东信里最常提到的就是股息率。所以很多人都误以为，脱离ROE仅仅依靠股息率便可分析出巴菲特投资案例的内在价值，但却始终不得其果。只因巴菲特虽然非常重视股息率，但却只是隐形参数。\n\n隐形参数5：ROE增长率\n\n巴菲特在股东手册里坦言：可以把ROE看作是内在价值的增长率。所以说，那些ROE稳增长的股票，便可适当高估。举例来说，20%的ROE增长率，1.2PR才算高估。反之则是：-20%的ROE增长率，0.8PR就算高估了。\n\n![Image](/static/article_images/648d9517-d8ac-45e4-a64e-2763d9e63eec.png)\n\n不得不说的是，市赚率并不适合估值成长股，反倒是PEG更适合。但如果能把ROE增长率也考虑进去，市赚率便可捕捉到少量的成长股！\n\n本文最后要说的是，市赚率的五大隐形参数都存在各种问题。增长率不稳定、负债率无法跨行业对比、长期国债利率短短几年就能翻N倍（2020～2023年的美元）。所以说，市赚率的“隐形参数”只能主打一个“模糊的正确”，否则就会导致“精确的错误”！\n\n有些时候，五大隐形参数无法兼顾，只能有所取舍。困境反转股，无法考虑增长率。科技股经常用回购替代分红，无法考虑股息率。周期股的ROE在景气年份里理应上涨就无法考虑ROE增长率。有鉴于此，投资既是科学也是艺术！\n\n@今日话题@闭嘴吧超超@博士王神经@曹国公李景隆@直言不讳的勇敢@陆冲河\n\n$贵州茅台(SH600519)$$招商银行(SH600036)$$中国恒大(03333)$\n",
            "tags": [],
            "created_at": 1769572546
        }
    ]
}